nagios/__init__.py
nagios/service/__init__.py
nagios/service/service_alive.py
nagios/sumologic/__init__.py
nagios/sumologic/last_message.py
omada_nagios-1.0.18.data/scripts/service-status-check
omada_nagios-1.0.18.data/scripts/sumologic_collector-last-message
omada_nagios-1.0.18.dist-info/DESCRIPTION.rst
omada_nagios-1.0.18.dist-info/METADATA
omada_nagios-1.0.18.dist-info/RECORD
omada_nagios-1.0.18.dist-info/WHEEL
omada_nagios-1.0.18.dist-info/metadata.json
omada_nagios-1.0.18.dist-info/top_level.txt
