Metadata-Version: 2.0
Name: omada-nagios
Version: 1.0.18
Summary: A framework for writing Nagios plugins
Home-page: https://github.com/omadahealth/omada-nagios
Author: Kevin Phillips
Author-email: kevin.phillips@omadahealth.com
License: MIT
Keywords: omada-nagios nagios monitoring
Platform: UNKNOWN
Classifier: Development Status :: 3 - Alpha
Classifier: Intended Audience :: System Administrators
Classifier: Topic :: System :: Monitoring
Classifier: License :: OSI Approved :: MIT License
Classifier: Programming Language :: Python :: 2
Classifier: Programming Language :: Python :: 2.6
Classifier: Programming Language :: Python :: 2.7
Requires-Dist: sumologic-sdk
Requires-Dist: requests
Provides-Extra: dev
Requires-Dist: check-manifest; extra == 'dev'
Requires-Dist: twine; extra == 'dev'
Provides-Extra: test
Requires-Dist: mock; extra == 'test'
Requires-Dist: pytest; extra == 'test'
